llmastar/__init__.py
llmastar/version.py
llmastar/dataset/__init__.py
llmastar/dataset/dataset.py
llmastar/env/__init__.py
llmastar/env/search/__init__.py
llmastar/env/search/env.py
llmastar/env/search/plotting.py
llmastar/model/__init__.py
llmastar/model/chatgpt.py
llmastar/model/llama3.py
llmastar/pather/__init__.py
llmastar/pather/a_star/__init__.py
llmastar/pather/a_star/a_star.py
llmastar/pather/llm_a_star/__init__.py
llmastar/pather/llm_a_star/llm_a_star.py
llmastar/pather/llm_a_star/prompt.py
llmastar/utils/__init__.py
llmastar/utils/filter.py
llmastar/utils/utils.py
tests/__init__.py
llm_astar-0.1.4.dist-info/LICENSE
llm_astar-0.1.4.dist-info/METADATA
llm_astar-0.1.4.dist-info/WHEEL
llm_astar-0.1.4.dist-info/top_level.txt
llm_astar-0.1.4.dist-info/RECORD
