Metadata-Version: 2.1
Name: llm-astar
Version: 0.1.4
Summary: LLM-A*: Large Language Model Enhanced Incremental Heuristic Search on Path Planning.
Home-page: https://github.com/SilinMeng0510/llm-astar
Download-URL: https://github.com/SilinMeng0510/llm-astar/archive/refs/heads/main.zip
Author: Silin Meng
Author-email: silinmeng@gmail.com
Keywords: LLMs,route planning,deep learning,neural networks,research,LLMs agent
License-File: LICENSE
Requires-Dist: setuptools ~=68.2.2
Requires-Dist: openai ==0.27.2
Requires-Dist: inquirer ~=3.2.4
Requires-Dist: shapely
Requires-Dist: matplotlib
Requires-Dist: numpy
Requires-Dist: transformers
Requires-Dist: torch
